LICENSE
README.md
setup.py
mediacloud_api_legacy.egg-info/PKG-INFO
mediacloud_api_legacy.egg-info/SOURCES.txt
mediacloud_api_legacy.egg-info/dependency_links.txt
mediacloud_api_legacy.egg-info/not-zip-safe
mediacloud_api_legacy.egg-info/requires.txt
mediacloud_api_legacy.egg-info/top_level.txt
mediacloud_legacy/__init__.py
mediacloud_legacy/api.py
mediacloud_legacy/error.py
mediacloud_legacy/storage.py
mediacloud_legacy/tags.py