Metadata-Version: 2.1
Name: mediacloud-api-legacy
Version: 3.13.1
Summary: Legacy Media Cloud API Client Library
Home-page: http://mediacloud.org
Author: Rahul Bhargava
Author-email: rahulb@mit.edu
License: MIT
Platform: UNKNOWN
Provides-Extra: db
License-File: LICENSE
